kuro.py
kuro-0.0.3.dist-info/entry_points.txt
kuro-0.0.3.dist-info/LICENSE
kuro-0.0.3.dist-info/WHEEL
kuro-0.0.3.dist-info/METADATA
kuro-0.0.3.dist-info/RECORD
